Paquetes/__init__.py
Paquetes/Adios/__init__.py
Paquetes/Adios/despedidas.py
Paquetes/Hola/__init__.py
Paquetes/Hola/test3.py
tests/__init__.py
tests/test_adios.py
tests/test_hola.py
Paquetes_franaser1985-6.0.dist-info/LICENSE
Paquetes_franaser1985-6.0.dist-info/METADATA
Paquetes_franaser1985-6.0.dist-info/WHEEL
Paquetes_franaser1985-6.0.dist-info/top_level.txt
Paquetes_franaser1985-6.0.dist-info/RECORD
